modulemeta/__init__.py
modulemeta-0.2.0a2.dist-info/LICENSE
modulemeta-0.2.0a2.dist-info/METADATA
modulemeta-0.2.0a2.dist-info/WHEEL
modulemeta-0.2.0a2.dist-info/top_level.txt
modulemeta-0.2.0a2.dist-info/RECORD
