Metadata-Version: 2.1
Name: modulemeta
Version: 0.2.0a2
Summary: A Module metaclass, to make your classes into modules.
Home-page: https://github.com/megawidget/python-module
Author: Igor Kaplounenko
Author-email: megawidget@gmail.com
License: MIT
Platform: UNKNOWN
Classifier: License :: OSI Approved :: MIT License
Classifier: Programming Language :: Python :: 3 :: Only
Classifier: Development Status :: 3 - Alpha
Classifier: Topic :: Software Development :: Libraries :: Python Modules
Requires-Python: >=3.9
License-File: LICENSE
